sscsv/controllers/CsvController.py
sscsv/controllers/DataFrameController.py
sscsv/run.py
sscsv/views/TableView.py
sscsv-0.1.1.dist-info/LICENSE
sscsv-0.1.1.dist-info/METADATA
sscsv-0.1.1.dist-info/WHEEL
sscsv-0.1.1.dist-info/entry_points.txt
sscsv-0.1.1.dist-info/RECORD
