Metadata-Version: 2.1
Name: sscsv
Version: 0.1.1
Summary: A tool designed for rapid data processing and filtering, specifically tailored for handling CSV files for log analysis.
Home-page: https://github.com/sumeshi/sscsv
License: MIT
Keywords: Security,DFIR,CSV
Author: sumeshi
Author-email: sum3sh1@protonmail.com
Requires-Python: >=3.11,<4.0
Classifier: License :: OSI Approved :: MIT License
Classifier: Programming Language :: Python :: 3
Classifier: Programming Language :: Python :: 3.11
Classifier: Programming Language :: Python :: 3.12
Requires-Dist: fire (>=0.6.0,<0.7.0)
Requires-Dist: polars (>=0.20.31,<0.21.0)
Requires-Dist: rich (>=13.7.1,<14.0.0)
Project-URL: Repository, https://github.com/sumeshi/sscsv
